liform/__init__.py
liform/utility.py
liform/commands/__init__.py
liform/commands/degrade.py
liform/commands/display.py
liform/commands/handler.py
liform/commands/processors.py
liform/handlers/__init__.py
liform/handlers/base.py
liform/handlers/dnf.py
liform/handlers/linode.py
liform/handlers/linode_constants.py
liform/handlers/linode_utility.py
liform/handlers/pip2.py
liform/handlers/pip3.py
liform/handlers/ssh.py
liform/resources/__init__.py
liform/resources/parsers.py
liform/resources/processors.py
liform/resources/state.py
liform-0.50.data/scripts/liform-cli
liform-0.50.dist-info/DESCRIPTION.rst
liform-0.50.dist-info/METADATA
liform-0.50.dist-info/RECORD
liform-0.50.dist-info/WHEEL
liform-0.50.dist-info/metadata.json
liform-0.50.dist-info/top_level.txt
