Metadata-Version: 2.0
Name: liform
Version: 0.50
Summary: Linode Server Orchestration
Home-page: https://bitbucket.org/triflesoft/liform
Author: TrifleSoft LLC
Author-email: support@triflesoft.org
License: BSD
Keywords: liform linode orchestration
Platform: UNKNOWN
Classifier: Development Status :: 3 - Alpha
Classifier: Intended Audience :: System Administrators
Classifier: Environment :: Console
Classifier: License :: OSI Approved :: BSD License
Classifier: Operating System :: POSIX :: Linux
Classifier: Programming Language :: Python :: 3 :: Only
Classifier: Programming Language :: Python :: 3.5
Classifier: Programming Language :: Python :: 3.6
Requires-Dist: Jinja2
Requires-Dist: linode-api
Requires-Dist: lxml
Requires-Dist: paramiko
